README.md
setup.cfg
setup.py
wwpdb/__init__.py
wwpdb.apps.msgmodule.egg-info/PKG-INFO
wwpdb.apps.msgmodule.egg-info/SOURCES.txt
wwpdb.apps.msgmodule.egg-info/dependency_links.txt
wwpdb.apps.msgmodule.egg-info/not-zip-safe
wwpdb.apps.msgmodule.egg-info/requires.txt
wwpdb.apps.msgmodule.egg-info/top_level.txt
wwpdb/apps/__init__.py
wwpdb/apps/msgmodule/__init__.py
wwpdb/apps/msgmodule/db/DataAccessLayer.py
wwpdb/apps/msgmodule/db/LockFile.py
wwpdb/apps/msgmodule/db/MessagingDataExport.py
wwpdb/apps/msgmodule/db/MessagingDataImport.py
wwpdb/apps/msgmodule/db/Models.py
wwpdb/apps/msgmodule/db/PdbxMessage.py
wwpdb/apps/msgmodule/db/PdbxMessageIo.py
wwpdb/apps/msgmodule/db/__init__.py
wwpdb/apps/msgmodule/depict/MessagingDepict.py
wwpdb/apps/msgmodule/depict/MessagingTemplates.py
wwpdb/apps/msgmodule/depict/__init__.py
wwpdb/apps/msgmodule/io/CompatIo.py
wwpdb/apps/msgmodule/io/DateUtil.py
wwpdb/apps/msgmodule/io/EmHeaderUtils.py
wwpdb/apps/msgmodule/io/MessagingDataExport.py
wwpdb/apps/msgmodule/io/MessagingDataImport.py
wwpdb/apps/msgmodule/io/MessagingIo.py
wwpdb/apps/msgmodule/io/__init__.py
wwpdb/apps/msgmodule/models/Message.py
wwpdb/apps/msgmodule/models/__init__.py
wwpdb/apps/msgmodule/util/AutoMessage.py
wwpdb/apps/msgmodule/util/DaInternalDb.py
wwpdb/apps/msgmodule/util/ExtractMessage.py
wwpdb/apps/msgmodule/util/MessagingDataRouter.py
wwpdb/apps/msgmodule/util/__init__.py
wwpdb/apps/msgmodule/util/dump_db_to_cif.py
wwpdb/apps/msgmodule/util/list_recent_messages.py
wwpdb/apps/msgmodule/webapp/MessagingWebApp.py
wwpdb/apps/msgmodule/webapp/__init__.py
wwpdb/apps/msgmodule/webapp/wsgi.py