Metadata-Version: 2.4
Name: wwpdb.apps.msgmodule
Version: 0.180
Summary: wwPDB messaging module
Home-page: https://github.com/rcsb/py-wwpdb_apps_ann_tasks_v2
Author: Ezra Peisach
Author-email: ezra.peisach@rcsb.org
License: Apache 2.0
Classifier: Development Status :: 3 - Alpha
Classifier: Intended Audience :: Developers
Classifier: Natural Language :: English
Classifier: License :: OSI Approved :: Apache Software License
Classifier: Programming Language :: Python
Classifier: Programming Language :: Python :: 2.7
Classifier: Programming Language :: Python :: 3
Classifier: Programming Language :: Python :: 3.6
Classifier: Programming Language :: Python :: 3.7
Requires-Dist: oslo.concurrency
Requires-Dist: wwpdb.io
Requires-Dist: wwpdb.utils.config>=0.52
Requires-Dist: wwpdb.utils.db
Requires-Dist: wwpdb.utils.session
Requires-Dist: wwpdb.utils.wf>=0.8
Requires-Dist: mmcif
Requires-Dist: mmcif.utils
Requires-Dist: wwpdb.utils.dp
Requires-Dist: wwpdb.utils.emdb>=0.17
Requires-Dist: wwpdb.apps.wf_engine
Requires-Dist: wwpdb.utils.nmr
Requires-Dist: pymysql
Requires-Dist: gemmi>=0.6.0
Provides-Extra: dev
Requires-Dist: check-manifest; extra == "dev"
Provides-Extra: test
Requires-Dist: coverage; extra == "test"
Dynamic: author
Dynamic: author-email
Dynamic: classifier
Dynamic: description
Dynamic: home-page
Dynamic: license
Dynamic: provides-extra
Dynamic: requires-dist
Dynamic: summary
